historian/postgresql/__init__.py
historian/postgresql/postgresqlfuncts.py
volttron_postgresql_historian-2.0.0rc1.dist-info/LICENSE
volttron_postgresql_historian-2.0.0rc1.dist-info/METADATA
volttron_postgresql_historian-2.0.0rc1.dist-info/WHEEL
volttron_postgresql_historian-2.0.0rc1.dist-info/entry_points.txt
volttron_postgresql_historian-2.0.0rc1.dist-info/RECORD
